resumelyzer_pro/__init__.py
resumelyzer_pro/api.py
resumelyzer_pro/auth.py
resumelyzer_pro/cli.py
resumelyzer_pro/endpoints.py
resumelyzer_pro-1.0.0.dist-info/METADATA
resumelyzer_pro-1.0.0.dist-info/WHEEL
resumelyzer_pro-1.0.0.dist-info/entry_points.txt
resumelyzer_pro-1.0.0.dist-info/top_level.txt
resumelyzer_pro-1.0.0.dist-info/RECORD
