Metadata-Version: 2.4
Name: resumelyzer-pro
Version: 1.0.0
Summary: Professional resume analysis API (paid version)
Requires-Python: >=3.8
Requires-Dist: requests>=2.25.0
Requires-Dist: stripe>=8.0.0
